symbolist/__init__.py
symbolist/fonts/avenir_black.woff
symbolist/symbolist.py
symbolist-0.1.0.dist-info/WHEEL
symbolist-0.1.0.dist-info/METADATA
symbolist-0.1.0.dist-info/RECORD
